polars_rng-0.1.0.dist-info/METADATA
polars_rng-0.1.0.dist-info/WHEEL
polars_rng/__init__.py
polars_rng/_core.abi3.so
polars_rng/helpers.py
polars_rng-0.1.0.dist-info/RECORD
