Metadata-Version: 2.4
Name: polars_rng
Version: 0.1.0
Requires-Dist: polars>=1.27.0
Summary: Random number generation as polars expressions
Author-email: Alistair Pattison <alistairpattison@gmail.com>
Requires-Python: >=3.13
